python_tuxexchange-0.0.2.dist-info/DESCRIPTION.rst
python_tuxexchange-0.0.2.dist-info/METADATA
python_tuxexchange-0.0.2.dist-info/RECORD
python_tuxexchange-0.0.2.dist-info/WHEEL
python_tuxexchange-0.0.2.dist-info/metadata.json
python_tuxexchange-0.0.2.dist-info/top_level.txt
tuxexchange/__init__.py
tuxexchange/test.py
tuxexchange/test_manual.py
tuxexchange/tuxexchange.py
