Metadata-Version: 2.0
Name: python-tuxexchange
Version: 0.0.2
Summary: Tux Exchange API wrapper for Python 2.7 (superceded by crypto-exchange-apis)
Home-page: https://github.com/init-industries/python-tuxexchange
Author: sneurlax
Author-email: sneurlax@gmail.com
License: MIT
Keywords: cryptocurrency exchange bitcoin trading
Platform: UNKNOWN
Classifier: Development Status :: 3 - Alpha
Classifier: Intended Audience :: Developers
Classifier: Topic :: Software Development :: Build Tools
Classifier: License :: OSI Approved :: MIT License
Classifier: Programming Language :: Python :: 2
Classifier: Programming Language :: Python :: 2.7
